<?xml version="1.0" encoding="UTF-8"?>
<export version="D">
  <design>
    <source>/home/mark/Nextcloud/Documents/surfncircuits/SnCProjects/NixiePowerSupply/KC_NixieSupply5vTo170vMini/NixieSupply5vto170vDCMBoostMini.sch</source>
    <date>Sat 05 Jun 2021 08:06:07 AM PDT</date>
    <tool>Eeschema 5.1.6-c6e7f7d~87~ubuntu20.04.1</tool>
    <sheet number="1" name="/" tstamps="/">
      <title_block>
        <title/>
        <company/>
        <rev/>
        <date/>
        <source>NixieSupply5vto170vDCMBoostMini.sch</source>
        <comment number="1" value=""/>
        <comment number="2" value=""/>
        <comment number="3" value=""/>
        <comment number="4" value=""/>
      </title_block>
    </sheet>
  </design>
  <components>
    <comp ref="D1">
      <value>ES1D</value>
      <footprint>Diodes_SMD:D_SMA</footprint>
      <datasheet>https://www.digikey.com/product-detail/en/on-semiconductor/ES1D/ES1DFSCT-ND/458940</datasheet>
      <fields>
        <field name="MPN">ES1D</field>
      </fields>
      <libsource lib="Device" part="D" description="Diode"/>
      <sheetpath names="/" tstamps="/"/>
      <tstamp>5884DA8B</tstamp>
    </comp>
    <comp ref="L3">
      <value>33uH</value>
      <footprint>NixieSupply5vto160vDCMBoost_socket:Choke_SMD_12x12mm_Wurth_WE-PD</footprint>
      <datasheet>https://www.digikey.com/products/en/inductors-coils-chokes/fixed-inductors/71?k=7447709330&amp;k=&amp;pkeyword=7447709330&amp;pv7=2&amp;mnonly=0&amp;ColumnSort=0&amp;page=1&amp;quantity=0&amp;ptm=0&amp;fid=0&amp;pageSize=25</datasheet>
      <fields>
        <field name="MAN">Wurth</field>
        <field name="MPN">7447709330</field>
      </fields>
      <libsource lib="NixieSupply5vto170vDCMBoostMini-rescue" part="L" description=""/>
      <sheetpath names="/" tstamps="/"/>
      <tstamp>5884DB9B</tstamp>
    </comp>
    <comp ref="R10">
      <value>0.1 1/2W</value>
      <footprint>Resistors_SMD:R_0805</footprint>
      <datasheet>https://www.digikey.com/product-detail/en/panasonic-electronic-components/ERJ-6DSFR10V/P19308CT-ND/6004663</datasheet>
      <fields>
        <field name="MAN">Panasonic</field>
        <field name="MPN">ERJ-6DSFR10V</field>
      </fields>
      <libsource lib="Device" part="R" description="Resistor"/>
      <sheetpath names="/" tstamps="/"/>
      <tstamp>5884DD2F</tstamp>
    </comp>
    <comp ref="U1">
      <value>UCC3803</value>
      <footprint>NixieSupply5vto160vDCMBoost_socket:SOIC-8-N</footprint>
      <datasheet>https://www.digikey.com/short/nw0qc0m8</datasheet>
      <fields>
        <field name="MAN">TI</field>
        <field name="MPN">UCC3803DTR</field>
      </fields>
      <libsource lib="NixieSupply5vto170vDCMBoostMini-rescue" part="AAC243" description=""/>
      <sheetpath names="/" tstamps="/"/>
      <tstamp>58854AD6</tstamp>
    </comp>
    <comp ref="C15">
      <value>560pF 250v</value>
      <footprint>Capacitors_SMD:C_0603</footprint>
      <datasheet>https://www.digikey.com/product-detail/en/kemet/C0603C561JAGAC7867/399-14990-1-ND/7382539</datasheet>
      <fields>
        <field name="MPN">C0603C561JAGAC7867</field>
      </fields>
      <libsource lib="Device" part="C" description="Unpolarized capacitor"/>
      <sheetpath names="/" tstamps="/"/>
      <tstamp>58854D96</tstamp>
    </comp>
    <comp ref="R8">
      <value>1k</value>
      <footprint>Resistors_SMD:R_0805</footprint>
      <datasheet>https://www.digikey.com/short/zhfh52p4</datasheet>
      <fields>
        <field name="MAN">Yageo</field>
        <field name="MPN">RC0805FR-071KL</field>
      </fields>
      <libsource lib="Device" part="R" description="Resistor"/>
      <sheetpath names="/" tstamps="/"/>
      <tstamp>588551A6</tstamp>
    </comp>
    <comp ref="C11">
      <value>1nF</value>
      <footprint>Capacitors_SMD:C_0805</footprint>
      <datasheet>https://www.digikey.com/short/9v2r4b4r</datasheet>
      <fields>
        <field name="MAN">KEMET</field>
        <field name="MPN">C0805C102M5RACTU</field>
      </fields>
      <libsource lib="Device" part="C" description="Unpolarized capacitor"/>
      <sheetpath names="/" tstamps="/"/>
      <tstamp>58855203</tstamp>
    </comp>
    <comp ref="R15">
      <value>634k</value>
      <footprint>Resistors_SMD:R_0805</footprint>
      <datasheet>https://www.digikey.com/short/2hqfm3bm</datasheet>
      <fields>
        <field name="MAN">Yageo</field>
        <field name="MPN">RC0805FR-07634KL</field>
      </fields>
      <libsource lib="Device" part="R" description="Resistor"/>
      <sheetpath names="/" tstamps="/"/>
      <tstamp>588552CB</tstamp>
    </comp>
    <comp ref="R16">
      <value>7.68k</value>
      <footprint>Resistors_SMD:R_0805</footprint>
      <datasheet>https://www.digikey.com/short/rv4d2w71</datasheet>
      <fields>
        <field name="MAN">Yageo</field>
        <field name="MPN">RC0805FR-077K68L</field>
      </fields>
      <libsource lib="Device" part="R" description="Resistor"/>
      <sheetpath names="/" tstamps="/"/>
      <tstamp>58855328</tstamp>
    </comp>
    <comp ref="R5">
      <value>0 Ohm</value>
      <footprint>Resistors_SMD:R_0805</footprint>
      <datasheet>https://www.digikey.com/short/4r0qnbv9</datasheet>
      <fields>
        <field name="MAN">Yageo</field>
        <field name="MPN">RC0805FR-070RL</field>
      </fields>
      <libsource lib="Device" part="R" description="Resistor"/>
      <sheetpath names="/" tstamps="/"/>
      <tstamp>5885549C</tstamp>
    </comp>
    <comp ref="C5">
      <value>220pF</value>
      <footprint>Capacitors_SMD:C_0805</footprint>
      <datasheet>https://www.digikey.com/short/dmv5m3jj</datasheet>
      <fields>
        <field name="MAN">KEMET</field>
        <field name="MPN">C0805C221M5RACTU</field>
      </fields>
      <libsource lib="Device" part="C" description="Unpolarized capacitor"/>
      <sheetpath names="/" tstamps="/"/>
      <tstamp>5885552D</tstamp>
    </comp>
    <comp ref="R3">
      <value>N.U.</value>
      <footprint>Resistors_SMD:R_0805</footprint>
      <libsource lib="Device" part="R" description="Resistor"/>
      <sheetpath names="/" tstamps="/"/>
      <tstamp>588555AD</tstamp>
    </comp>
    <comp ref="R2">
      <value>60.4k</value>
      <footprint>Resistors_SMD:R_0805</footprint>
      <datasheet>https://www.digikey.com/short/tnrw9ntp</datasheet>
      <fields>
        <field name="MAN">Yageo</field>
        <field name="MPN">RC0805FR-0760K4L</field>
      </fields>
      <libsource lib="Device" part="R" description="Resistor"/>
      <sheetpath names="/" tstamps="/"/>
      <tstamp>58855807</tstamp>
    </comp>
    <comp ref="C7">
      <value>430pF</value>
      <footprint>Capacitors_SMD:C_0805</footprint>
      <datasheet>https://www.digikey.com/product-detail/en/samsung-electro-mechanics/CL21C431JBANNNC/1276-2659-1-ND/3890745</datasheet>
      <fields>
        <field name="MPN">CL21C431JBANNNC</field>
      </fields>
      <libsource lib="Device" part="C" description="Unpolarized capacitor"/>
      <sheetpath names="/" tstamps="/"/>
      <tstamp>58855871</tstamp>
    </comp>
    <comp ref="Q1">
      <value>FDS2672CT</value>
      <footprint>etaclock:SOIC-8-N</footprint>
      <datasheet>https://www.digikey.com/product-detail/en/on-semiconductor/FDS2672/FDS2672CT-ND/1217902</datasheet>
      <fields>
        <field name="MAN">On-Semi</field>
        <field name="MPN">FDS2672CT-ND</field>
      </fields>
      <libsource lib="NixieSupply5vto170vDCMBoostMini-rescue" part="FDMS86255ET150" description=""/>
      <sheetpath names="/" tstamps="/"/>
      <tstamp>59606CBE</tstamp>
    </comp>
    <comp ref="C2">
      <value>1uF 250v</value>
      <footprint>Capacitors_SMD:C_1812_HandSoldering</footprint>
      <datasheet>https://www.digikey.com/product-detail/en/tdk-corporation/C4532X7T2E105M250KE/445-6835-1-ND/2616466</datasheet>
      <fields>
        <field name="MPN">C4532X7T2E105M250KE</field>
      </fields>
      <libsource lib="Device" part="C" description="Unpolarized capacitor"/>
      <sheetpath names="/" tstamps="/"/>
      <tstamp>59700BD6</tstamp>
    </comp>
    <comp ref="C1">
      <value>1uF 250v</value>
      <footprint>Capacitors_SMD:C_1812_HandSoldering</footprint>
      <datasheet>https://www.digikey.com/product-detail/en/tdk-corporation/C4532X7T2E105M250KE/445-6835-1-ND/2616466</datasheet>
      <fields>
        <field name="MPN">C4532X7T2E105M250KE</field>
      </fields>
      <libsource lib="Device" part="C" description="Unpolarized capacitor"/>
      <sheetpath names="/" tstamps="/"/>
      <tstamp>597025DB</tstamp>
    </comp>
    <comp ref="C6">
      <value>100pF 250v</value>
      <footprint>Capacitors_SMD:C_0805</footprint>
      <datasheet>https://www.digikey.com/products/en/capacitors/ceramic-capacitors/60?k=C0805C101JAGAC7800&amp;k=&amp;pkeyword=C0805C101JAGAC7800&amp;pv7=2&amp;quantity=0&amp;ColumnSort=0&amp;page=1&amp;pageSize=25</datasheet>
      <fields>
        <field name="MPN">C0805C101JAGAC7800</field>
      </fields>
      <libsource lib="Device" part="C" description="Unpolarized capacitor"/>
      <sheetpath names="/" tstamps="/"/>
      <tstamp>5A3FE39A</tstamp>
    </comp>
    <comp ref="C9">
      <value>100uF 16v</value>
      <footprint>Capacitors_SMD:C_1210</footprint>
      <datasheet>https://www.digikey.com/product-detail/en/taiyo-yuden/EMK325ABJ107MM-P/587-5426-2-ND/7067011</datasheet>
      <fields>
        <field name="MPN">EMK325ABJ107MM-P</field>
      </fields>
      <libsource lib="Device" part="C" description="Unpolarized capacitor"/>
      <sheetpath names="/" tstamps="/"/>
      <tstamp>5A46B83F</tstamp>
    </comp>
    <comp ref="J5">
      <value>CONN_01X01</value>
      <footprint>Mounting_Holes:MountingHole_2.2mm_M2</footprint>
      <libsource lib="Connector_Generic" part="Conn_01x01" description="Generic connector, single row, 01x01, script generated (kicad-library-utils/schlib/autogen/connector/)"/>
      <sheetpath names="/" tstamps="/"/>
      <tstamp>5A46B464</tstamp>
    </comp>
    <comp ref="J3">
      <value>CONN_01X01</value>
      <footprint>Mounting_Holes:MountingHole_2.2mm_M2_Pad</footprint>
      <libsource lib="Connector_Generic" part="Conn_01x01" description="Generic connector, single row, 01x01, script generated (kicad-library-utils/schlib/autogen/connector/)"/>
      <sheetpath names="/" tstamps="/"/>
      <tstamp>5A46B52B</tstamp>
    </comp>
    <comp ref="J4">
      <value>CONN_01X01</value>
      <footprint>Mounting_Holes:MountingHole_2.2mm_M2</footprint>
      <libsource lib="Connector_Generic" part="Conn_01x01" description="Generic connector, single row, 01x01, script generated (kicad-library-utils/schlib/autogen/connector/)"/>
      <sheetpath names="/" tstamps="/"/>
      <tstamp>5A46B5EB</tstamp>
    </comp>
    <comp ref="J2">
      <value>CONN_01X01</value>
      <footprint>Mounting_Holes:MountingHole_2.2mm_M2_Pad</footprint>
      <libsource lib="Connector_Generic" part="Conn_01x01" description="Generic connector, single row, 01x01, script generated (kicad-library-utils/schlib/autogen/connector/)"/>
      <sheetpath names="/" tstamps="/"/>
      <tstamp>5A46B2DF</tstamp>
    </comp>
    <comp ref="C10">
      <value>0.1uF 16v</value>
      <footprint>Capacitors_SMD:C_0805</footprint>
      <datasheet>https://www.digikey.com/short/tcz8722d</datasheet>
      <fields>
        <field name="MAN">KEMET</field>
        <field name="MPN">C0805C104K3RACTU</field>
      </fields>
      <libsource lib="Device" part="C" description="Unpolarized capacitor"/>
      <sheetpath names="/" tstamps="/"/>
      <tstamp>5A478653</tstamp>
    </comp>
    <comp ref="R12">
      <value>4.12k</value>
      <footprint>Resistors_SMD:R_0805</footprint>
      <datasheet>https://www.digikey.com/short/t85fjzmz</datasheet>
      <fields>
        <field name="MAN">Yageo</field>
        <field name="MPN">RC0805FR-074K12L</field>
      </fields>
      <libsource lib="Device" part="R" description="Resistor"/>
      <sheetpath names="/" tstamps="/"/>
      <tstamp>5A4792E0</tstamp>
    </comp>
    <comp ref="C3">
      <value>0.1uF 250v</value>
      <footprint>Capacitors_SMD:C_0805</footprint>
      <datasheet>https://www.digikey.com/short/rfdn84mq</datasheet>
      <fields>
        <field name="MAN">TDK</field>
        <field name="MPN">CGA4J3X7T2E104M125AE</field>
      </fields>
      <libsource lib="Device" part="C" description="Unpolarized capacitor"/>
      <sheetpath names="/" tstamps="/"/>
      <tstamp>5A45D816</tstamp>
    </comp>
    <comp ref="L5">
      <value>60ohm 100Mhz</value>
      <footprint>Resistors_SMD:R_0805</footprint>
      <datasheet>https://www.digikey.com/product-detail/en/taiyo-yuden/BKP2125HS600-T/587-1932-1-ND/1465402</datasheet>
      <fields>
        <field name="MPN">BKP2125HS600-T</field>
      </fields>
      <libsource lib="NixieSupply5vto170vDCMBoostMini-rescue" part="L" description=""/>
      <sheetpath names="/" tstamps="/"/>
      <tstamp>5885A4D9</tstamp>
    </comp>
    <comp ref="C12">
      <value>0.1uF 250v</value>
      <footprint>Capacitors_SMD:C_0805</footprint>
      <datasheet>https://www.digikey.com/short/rfdn84mq</datasheet>
      <fields>
        <field name="MAN">TDK</field>
        <field name="MPN">CGA4J3X7T2E104M125AE</field>
      </fields>
      <libsource lib="Device" part="C" description="Unpolarized capacitor"/>
      <sheetpath names="/" tstamps="/"/>
      <tstamp>5974DAD8</tstamp>
    </comp>
    <comp ref="L2">
      <value>60ohm 100Mhz</value>
      <footprint>Resistors_SMD:R_0805</footprint>
      <datasheet>https://www.digikey.com/product-detail/en/taiyo-yuden/BKP2125HS600-T/587-1932-1-ND/1465402</datasheet>
      <fields>
        <field name="MPN">BKP2125HS600-T</field>
      </fields>
      <libsource lib="NixieSupply5vto170vDCMBoostMini-rescue" part="L" description=""/>
      <sheetpath names="/" tstamps="/"/>
      <tstamp>58859FC4</tstamp>
    </comp>
    <comp ref="C18">
      <value>0.1uF</value>
      <footprint>Capacitors_SMD:C_0805</footprint>
      <datasheet>https://www.digikey.com/short/tcz8722d</datasheet>
      <fields>
        <field name="MAN">KEMET</field>
        <field name="MPN">C0805C104K3RACTU</field>
      </fields>
      <libsource lib="Device" part="C" description="Unpolarized capacitor"/>
      <sheetpath names="/" tstamps="/"/>
      <tstamp>5A40B0B2</tstamp>
    </comp>
    <comp ref="C16">
      <value>100uF 16v</value>
      <footprint>Capacitors_SMD:C_1210</footprint>
      <datasheet>https://www.digikey.com/product-detail/en/taiyo-yuden/EMK325ABJ107MM-P/587-5426-2-ND/7067011</datasheet>
      <fields>
        <field name="MPN">EMK325ABJ107MM-P</field>
      </fields>
      <libsource lib="Device" part="C" description="Unpolarized capacitor"/>
      <sheetpath names="/" tstamps="/"/>
      <tstamp>5A40AC1C</tstamp>
    </comp>
    <comp ref="R7">
      <value>2k</value>
      <footprint>Resistors_SMD:R_0805</footprint>
      <datasheet>https://www.digikey.com/short/795bprhd</datasheet>
      <fields>
        <field name="MAN">Yageo</field>
        <field name="MPN">RC0805FR-072KL</field>
      </fields>
      <libsource lib="Device" part="R" description="Resistor"/>
      <sheetpath names="/" tstamps="/"/>
      <tstamp>5A408EBF</tstamp>
    </comp>
    <comp ref="R9">
      <value>100k</value>
      <footprint>Resistors_SMD:R_0805</footprint>
      <datasheet>https://www.digikey.com/short/qzj2m8ht</datasheet>
      <fields>
        <field name="MAN">Yageo</field>
        <field name="MPN">RC0805FR-07100KL</field>
      </fields>
      <libsource lib="Device" part="R" description="Resistor"/>
      <sheetpath names="/" tstamps="/"/>
      <tstamp>5A408DDF</tstamp>
    </comp>
    <comp ref="C14">
      <value>47uF 16v</value>
      <footprint>Capacitors_SMD:C_1210</footprint>
      <datasheet>https://www.digikey.com/product-detail/en/taiyo-yuden/EMK325BJ476MM-P/587-5436-1-ND/7067112</datasheet>
      <fields>
        <field name="MPN">EMK325BJ476MM-P</field>
      </fields>
      <libsource lib="Device" part="C" description="Unpolarized capacitor"/>
      <sheetpath names="/" tstamps="/"/>
      <tstamp>5A408B31</tstamp>
    </comp>
    <comp ref="R1">
      <value>1k</value>
      <footprint>Resistors_SMD:R_0805</footprint>
      <datasheet>https://www.digikey.com/short/zhfh52p4</datasheet>
      <fields>
        <field name="MAN">Yageo</field>
        <field name="MPN">RC0805FR-071KL</field>
      </fields>
      <libsource lib="Device" part="R" description="Resistor"/>
      <sheetpath names="/" tstamps="/"/>
      <tstamp>5A3FC05D</tstamp>
    </comp>
    <comp ref="R4">
      <value>100k</value>
      <footprint>Resistors_SMD:R_0805</footprint>
      <datasheet>https://www.digikey.com/short/qzj2m8ht</datasheet>
      <fields>
        <field name="MAN">Yageo</field>
        <field name="MPN">RC0805FR-07100KL</field>
      </fields>
      <libsource lib="Device" part="R" description="Resistor"/>
      <sheetpath names="/" tstamps="/"/>
      <tstamp>5A3FC312</tstamp>
    </comp>
    <comp ref="P1">
      <value>USB_OTG</value>
      <footprint>NixieSupply5vto160vDCMBoost_socket:USB_Micro-B_Wurth_3A_Non-OVAL-Drill</footprint>
      <datasheet>https://www.digikey.com/product-detail/en/wurth-electronics-inc/629105150521/732-5960-1-ND/5047555</datasheet>
      <fields>
        <field name="MAN">Wurth</field>
        <field name="MPN">629105150521</field>
      </fields>
      <libsource lib="NixieSupply5vto170vDCMBoostMini-rescue" part="USB_OTG" description=""/>
      <sheetpath names="/" tstamps="/"/>
      <tstamp>5A51695C</tstamp>
    </comp>
    <comp ref="D2">
      <value>BAT54</value>
      <footprint>Diodes_SMD:D_SOD-323_HandSoldering</footprint>
      <datasheet>https://www.digikey.com/product-detail/en/diodes-incorporated/BAT54WS-7-F/BAT54WS-FDICT-ND/804892</datasheet>
      <fields>
        <field name="MPN">BAT54WS-7-F</field>
      </fields>
      <libsource lib="Device" part="D_Schottky" description="Schottky diode"/>
      <sheetpath names="/" tstamps="/"/>
      <tstamp>5A4626BB</tstamp>
    </comp>
    <comp ref="Q26">
      <value>MMBTA42</value>
      <footprint>TO_SOT_Packages_SMD:SOT-23</footprint>
      <datasheet>http://www.digikey.com/product-detail/en/micro-commercial-co/MMBTA42-TP/MMBTA42TPMSCT-ND/717401</datasheet>
      <fields>
        <field name="MPN">MMBTA42</field>
      </fields>
      <libsource lib="Transistor_BJT" part="MMBT3904" description="0.2A Ic, 40V Vce, Small Signal NPN Transistor, SOT-23"/>
      <sheetpath names="/" tstamps="/"/>
      <tstamp>5A7755E7</tstamp>
    </comp>
    <comp ref="J6">
      <value>Screw_Terminal_1x03</value>
      <footprint>TerminalBlock_Phoenix:TerminalBlock_Phoenix_MPT-2.54mm_3pol</footprint>
      <datasheet>https://www.digikey.com/product-detail/en/phoenix-contact/1725669/277-1274-ND/267463</datasheet>
      <fields>
        <field name="MAN">Phoenix</field>
        <field name="MPN">1725669</field>
      </fields>
      <libsource lib="NixieSupply5vto170vDCMBoostMini-rescue" part="Screw_Terminal_1x03" description=""/>
      <sheetpath names="/" tstamps="/"/>
      <tstamp>5AB1F989</tstamp>
    </comp>
    <comp ref="J1">
      <value>Screw_Terminal_1x02</value>
      <footprint>TerminalBlock_Phoenix:TerminalBlock_Phoenix_MPT-2.54mm_2pol</footprint>
      <datasheet>https://www.digikey.com/product-detail/en/phoenix-contact/1725656/277-1273-ND/267462</datasheet>
      <fields>
        <field name="MAN">Phoenix</field>
        <field name="MPN">1725656</field>
      </fields>
      <libsource lib="NixieSupply5vto170vDCMBoostMini-rescue" part="Screw_Terminal_1x02" description=""/>
      <sheetpath names="/" tstamps="/"/>
      <tstamp>5AB1F890</tstamp>
    </comp>
  </components>
  <libparts>
    <libpart lib="Connector_Generic" part="Conn_01x01">
      <description>Generic connector, single row, 01x01, script generated (kicad-library-utils/schlib/autogen/connector/)</description>
      <docs>~</docs>
      <footprints>
        <fp>Connector*:*_1x??_*</fp>
      </footprints>
      <fields>
        <field name="Reference">J</field>
        <field name="Value">Conn_01x01</field>
      </fields>
      <pins>
        <pin num="1" name="Pin_1" type="passive"/>
      </pins>
    </libpart>
    <libpart lib="Device" part="C">
      <description>Unpolarized capacitor</description>
      <docs>~</docs>
      <footprints>
        <fp>C_*</fp>
      </footprints>
      <fields>
        <field name="Reference">C</field>
        <field name="Value">C</field>
      </fields>
      <pins>
        <pin num="1" name="~" type="passive"/>
        <pin num="2" name="~" type="passive"/>
      </pins>
    </libpart>
    <libpart lib="Device" part="D">
      <description>Diode</description>
      <docs>~</docs>
      <footprints>
        <fp>TO-???*</fp>
        <fp>*_Diode_*</fp>
        <fp>*SingleDiode*</fp>
        <fp>D_*</fp>
      </footprints>
      <fields>
        <field name="Reference">D</field>
        <field name="Value">D</field>
      </fields>
      <pins>
        <pin num="1" name="K" type="passive"/>
        <pin num="2" name="A" type="passive"/>
      </pins>
    </libpart>
    <libpart lib="Device" part="D_Schottky">
      <description>Schottky diode</description>
      <docs>~</docs>
      <footprints>
        <fp>TO-???*</fp>
        <fp>*_Diode_*</fp>
        <fp>*SingleDiode*</fp>
        <fp>D_*</fp>
      </footprints>
      <fields>
        <field name="Reference">D</field>
        <field name="Value">D_Schottky</field>
      </fields>
      <pins>
        <pin num="1" name="K" type="passive"/>
        <pin num="2" name="A" type="passive"/>
      </pins>
    </libpart>
    <libpart lib="Device" part="R">
      <description>Resistor</description>
      <docs>~</docs>
      <footprints>
        <fp>R_*</fp>
      </footprints>
      <fields>
        <field name="Reference">R</field>
        <field name="Value">R</field>
      </fields>
      <pins>
        <pin num="1" name="~" type="passive"/>
        <pin num="2" name="~" type="passive"/>
      </pins>
    </libpart>
    <libpart lib="NixieSupply5vto170vDCMBoostMini-rescue" part="AAC243">
      <fields>
        <field name="Reference">U</field>
        <field name="Value">AAC243</field>
      </fields>
      <pins>
        <pin num="1" name="COMP" type="output"/>
        <pin num="2" name="FB" type="input"/>
        <pin num="3" name="Isense" type="input"/>
        <pin num="4" name="R/C" type="input"/>
        <pin num="5" name="GND" type="passive"/>
        <pin num="6" name="OUT" type="output"/>
        <pin num="7" name="Vcc" type="power_in"/>
        <pin num="8" name="Vref" type="output"/>
      </pins>
    </libpart>
    <libpart lib="NixieSupply5vto170vDCMBoostMini-rescue" part="FDMS86255ET150">
      <footprints>
        <fp>SON*</fp>
      </footprints>
      <fields>
        <field name="Reference">Q</field>
        <field name="Value">FDMS86255ET150</field>
        <field name="Footprint">TO_SOT_Packages_SMD:TDSON-8-1</field>
      </fields>
      <pins>
        <pin num="1" name="S" type="passive"/>
        <pin num="2" name="S" type="passive"/>
        <pin num="3" name="S" type="passive"/>
        <pin num="4" name="G" type="passive"/>
        <pin num="5" name="D" type="passive"/>
        <pin num="6" name="D" type="passive"/>
        <pin num="7" name="D" type="passive"/>
        <pin num="8" name="D" type="passive"/>
      </pins>
    </libpart>
    <libpart lib="NixieSupply5vto170vDCMBoostMini-rescue" part="L">
      <footprints>
        <fp>Choke_*</fp>
        <fp>*Coil*</fp>
        <fp>Inductor_*</fp>
        <fp>L_*</fp>
      </footprints>
      <fields>
        <field name="Reference">L</field>
        <field name="Value">L</field>
      </fields>
      <pins>
        <pin num="1" name="1" type="passive"/>
        <pin num="2" name="2" type="passive"/>
      </pins>
    </libpart>
    <libpart lib="NixieSupply5vto170vDCMBoostMini-rescue" part="Screw_Terminal_1x02">
      <footprints>
        <fp>bornier2</fp>
        <fp>TerminalBlock*2pol</fp>
      </footprints>
      <fields>
        <field name="Reference">J</field>
        <field name="Value">Screw_Terminal_1x02</field>
      </fields>
      <pins>
        <pin num="1" name="~" type="passive"/>
        <pin num="2" name="~" type="passive"/>
      </pins>
    </libpart>
    <libpart lib="NixieSupply5vto170vDCMBoostMini-rescue" part="Screw_Terminal_1x03">
      <footprints>
        <fp>bornier3</fp>
        <fp>TerminalBlock*3pol</fp>
      </footprints>
      <fields>
        <field name="Reference">J</field>
        <field name="Value">Screw_Terminal_1x03</field>
      </fields>
      <pins>
        <pin num="1" name="~" type="passive"/>
        <pin num="2" name="~" type="passive"/>
        <pin num="3" name="~" type="passive"/>
      </pins>
    </libpart>
    <libpart lib="NixieSupply5vto170vDCMBoostMini-rescue" part="USB_OTG">
      <footprints>
        <fp>USB*</fp>
      </footprints>
      <fields>
        <field name="Reference">J</field>
        <field name="Value">USB_OTG</field>
      </fields>
      <pins>
        <pin num="1" name="VBUS" type="power_in"/>
        <pin num="2" name="D-" type="passive"/>
        <pin num="3" name="D+" type="passive"/>
        <pin num="4" name="ID" type="passive"/>
        <pin num="5" name="GND" type="power_in"/>
        <pin num="6" name="Shield" type="passive"/>
      </pins>
    </libpart>
    <libpart lib="Transistor_BJT" part="BC817">
      <aliases>
        <alias>BC818</alias>
        <alias>BC846</alias>
        <alias>BC847</alias>
        <alias>BC848</alias>
        <alias>BC849</alias>
        <alias>BC850</alias>
        <alias>MMBT3904</alias>
        <alias>MMBT5550L</alias>
        <alias>MMBT5551L</alias>
      </aliases>
      <description>0.8A Ic, 45V Vce, NPN Transistor, SOT-23</description>
      <docs>https://www.onsemi.com/pub/Collateral/BC818-D.pdf</docs>
      <footprints>
        <fp>SOT?23*</fp>
      </footprints>
      <fields>
        <field name="Reference">Q</field>
        <field name="Value">BC817</field>
        <field name="Footprint">Package_TO_SOT_SMD:SOT-23</field>
      </fields>
      <pins>
        <pin num="1" name="B" type="input"/>
        <pin num="2" name="E" type="passive"/>
        <pin num="3" name="C" type="passive"/>
      </pins>
    </libpart>
  </libparts>
  <libraries>
    <library logical="Connector_Generic">
      <uri>/home/mark/Dropbox/personal/Kicad5-1-6/kicad-symbols/Connector_Generic.lib</uri>
    </library>
    <library logical="Device">
      <uri>/home/mark/Dropbox/personal/Kicad5-1-6/kicad-symbols/Device.lib</uri>
    </library>
    <library logical="NixieSupply5vto170vDCMBoostMini-rescue">
      <uri>/home/mark/Nextcloud/Documents/surfncircuits/SnCProjects/NixiePowerSupply/KC_NixieSupply5vTo170vMini/NixieSupply5vto170vDCMBoostMini-rescue.lib</uri>
    </library>
    <library logical="Transistor_BJT">
      <uri>/home/mark/Dropbox/personal/Kicad5-1-6/kicad-symbols/Transistor_BJT.lib</uri>
    </library>
  </libraries>
  <nets>
    <net code="1" name="Net-(Q26-Pad1)">
      <node ref="Q26" pin="1"/>
      <node ref="R4" pin="1"/>
      <node ref="R1" pin="1"/>
    </net>
    <net code="2" name="Net-(C14-Pad1)">
      <node ref="R7" pin="1"/>
      <node ref="C14" pin="1"/>
      <node ref="D2" pin="1"/>
      <node ref="R9" pin="2"/>
      <node ref="Q26" pin="3"/>
    </net>
    <net code="3" name="Net-(C5-Pad2)">
      <node ref="C5" pin="2"/>
      <node ref="R5" pin="2"/>
    </net>
    <net code="4" name="Net-(C5-Pad1)">
      <node ref="D2" pin="2"/>
      <node ref="C5" pin="1"/>
      <node ref="U1" pin="1"/>
      <node ref="R3" pin="2"/>
    </net>
    <net code="5" name="Net-(C7-Pad1)">
      <node ref="R2" pin="1"/>
      <node ref="U1" pin="4"/>
      <node ref="C7" pin="1"/>
    </net>
    <net code="6" name="Net-(C10-Pad1)">
      <node ref="R12" pin="2"/>
      <node ref="U1" pin="8"/>
      <node ref="R2" pin="2"/>
      <node ref="C10" pin="1"/>
    </net>
    <net code="7" name="Net-(C9-Pad1)">
      <node ref="U1" pin="7"/>
      <node ref="C9" pin="1"/>
      <node ref="L3" pin="2"/>
      <node ref="L2" pin="1"/>
    </net>
    <net code="8" name="+160V">
      <node ref="J1" pin="2"/>
      <node ref="J1" pin="1"/>
      <node ref="C3" pin="1"/>
      <node ref="L5" pin="1"/>
    </net>
    <net code="9" name="GND">
      <node ref="C7" pin="2"/>
      <node ref="Q26" pin="2"/>
      <node ref="C15" pin="2"/>
      <node ref="J2" pin="1"/>
      <node ref="J3" pin="1"/>
      <node ref="C12" pin="2"/>
      <node ref="R10" pin="2"/>
      <node ref="U1" pin="5"/>
      <node ref="R16" pin="2"/>
      <node ref="C3" pin="2"/>
      <node ref="C2" pin="2"/>
      <node ref="C10" pin="2"/>
      <node ref="C1" pin="2"/>
      <node ref="C11" pin="2"/>
      <node ref="R9" pin="1"/>
      <node ref="C9" pin="2"/>
      <node ref="J6" pin="1"/>
      <node ref="C14" pin="2"/>
      <node ref="P1" pin="6"/>
      <node ref="C16" pin="2"/>
      <node ref="C18" pin="2"/>
      <node ref="P1" pin="5"/>
    </net>
    <net code="10" name="5v_Power">
      <node ref="C16" pin="1"/>
      <node ref="C18" pin="1"/>
      <node ref="L2" pin="2"/>
      <node ref="R7" pin="2"/>
      <node ref="P1" pin="1"/>
      <node ref="J6" pin="3"/>
      <node ref="R4" pin="2"/>
    </net>
    <net code="11" name="N_ENABLE">
      <node ref="J6" pin="2"/>
      <node ref="R1" pin="2"/>
    </net>
    <net code="12" name="Net-(Q1-Pad4)">
      <node ref="U1" pin="6"/>
      <node ref="Q1" pin="4"/>
    </net>
    <net code="13" name="Net-(C15-Pad1)">
      <node ref="Q1" pin="7"/>
      <node ref="C15" pin="1"/>
      <node ref="Q1" pin="8"/>
      <node ref="Q1" pin="6"/>
      <node ref="Q1" pin="5"/>
      <node ref="L3" pin="1"/>
      <node ref="D1" pin="2"/>
    </net>
    <net code="14" name="Net-(C6-Pad2)">
      <node ref="R5" pin="1"/>
      <node ref="R16" pin="1"/>
      <node ref="R15" pin="2"/>
      <node ref="U1" pin="2"/>
      <node ref="R3" pin="1"/>
      <node ref="C6" pin="2"/>
    </net>
    <net code="15" name="Net-(C1-Pad1)">
      <node ref="C12" pin="1"/>
      <node ref="L5" pin="2"/>
      <node ref="D1" pin="1"/>
      <node ref="C2" pin="1"/>
      <node ref="C6" pin="1"/>
      <node ref="C1" pin="1"/>
      <node ref="R15" pin="1"/>
    </net>
    <net code="16" name="Net-(C11-Pad1)">
      <node ref="R8" pin="2"/>
      <node ref="C11" pin="1"/>
      <node ref="U1" pin="3"/>
      <node ref="R12" pin="1"/>
    </net>
    <net code="17" name="Net-(Q1-Pad1)">
      <node ref="Q1" pin="1"/>
      <node ref="Q1" pin="3"/>
      <node ref="Q1" pin="2"/>
      <node ref="R10" pin="1"/>
      <node ref="R8" pin="1"/>
    </net>
    <net code="18" name="Net-(P1-Pad4)">
      <node ref="P1" pin="4"/>
    </net>
    <net code="19" name="Net-(P1-Pad3)">
      <node ref="P1" pin="3"/>
    </net>
    <net code="20" name="Net-(P1-Pad2)">
      <node ref="P1" pin="2"/>
    </net>
    <net code="21" name="Net-(J4-Pad1)">
      <node ref="J4" pin="1"/>
    </net>
    <net code="22" name="Net-(J5-Pad1)">
      <node ref="J5" pin="1"/>
    </net>
  </nets>
</export>
